web3connectpy/__init__.py
web3connectpy/core.py
web3connectpy-0.1.0.dist-info/METADATA
web3connectpy-0.1.0.dist-info/WHEEL
web3connectpy-0.1.0.dist-info/top_level.txt
web3connectpy-0.1.0.dist-info/RECORD
